chemistry/__init__.py
chemistry/conversions.py
chemistry/formulas.py
chemistry/periodic.json
chemistry/periodic.py
chemistry_ch-0.2.6.dist-info/LICENSE
chemistry_ch-0.2.6.dist-info/METADATA
chemistry_ch-0.2.6.dist-info/WHEEL
chemistry_ch-0.2.6.dist-info/top_level.txt
chemistry_ch-0.2.6.dist-info/RECORD
