Metadata-Version: 2.1
Name: chemistry-ch
Version: 0.2.6
Summary: Python library for chemistry equations and formulas.
Home-page: https://github.com/calebyhan/chemistry
Author: Caleb Han
Author-email: calebhantech@gmail.com
License: MIT
Classifier: License :: OSI Approved :: MIT License
Classifier: Programming Language :: Python :: 3
Classifier: Operating System :: OS Independent
License-File: LICENSE
